LimanRSP/__init__.py
LimanRSP/enums.py
LimanRSP/signal.py
LimanRSP-0.1.7.dist-info/LICENSE
LimanRSP-0.1.7.dist-info/METADATA
LimanRSP-0.1.7.dist-info/WHEEL
LimanRSP-0.1.7.dist-info/top_level.txt
LimanRSP-0.1.7.dist-info/RECORD
