Metadata-Version: 2.1
Name: LimanRSP
Version: 0.1.7
Summary: Liman the realtime signal processing library
Home-page: https://liman-trade.com
Author: Nikita Besednyi
Author-email: nikmac10x@gmail.com
Project-URL: GitHub, https://github.com
Keywords: realtime signal processing
Classifier: Programming Language :: Python :: 3.11
Classifier: License :: OSI Approved :: MIT License
Classifier: Operating System :: OS Independent
Requires-Python: >=3.6
License-File: LICENSE
Requires-Dist: scipy==1.14.1
